torch_logs/__init__.py
torch_logs/imports.py
torch_logs/logger.py
torch_logs/training.py
torch_logs/utils.py
torch_logs-0.3.0.dist-info/WHEEL
torch_logs-0.3.0.dist-info/METADATA
torch_logs-0.3.0.dist-info/RECORD
