Metadata-Version: 2.1
Name: torch-logs
Version: 0.3.0
Summary: 
License: MIT
Author: yohan-pg
Author-email: pg.yohan@gmail.com
Requires-Python: >=3.10,<4.0
Classifier: License :: OSI Approved :: MIT License
Classifier: Programming Language :: Python :: 3
Classifier: Programming Language :: Python :: 3.10
Requires-Dist: pandas (>=1.4.2,<2.0.0)
Requires-Dist: plotly (>=5.8.0,<6.0.0)
Requires-Dist: torch (>=1.11.0,<2.0.0)
Requires-Dist: torchvision (>=0.12.0,<0.13.0)
